Metadata-Version: 2.4
Name: llama-blockchain-llamasearch
Version: 0.1.0
Summary: Blockchain components for the LlamaAI Ecosystem (verification, contracts, provenance).
Project-URL: Homepage, https://github.com/yourusername/llamasearchai-git2-copy
Author-email: llama-blockchain-llamasearch <nikjois@llamasearch.ai>
License: MIT
License-File: LICENSE
Keywords: blockchain,contract,llama,nft,provenance,verification
Classifier: Development Status :: 3 - Alpha
Classifier: Intended Audience :: Developers
Classifier: License :: OSI Approved :: MIT License
Classifier: Programming Language :: Python :: 3
Requires-Python: >=3.8
Provides-Extra: dev
Requires-Dist: black>=23.0.0; extra == 'dev'
Requires-Dist: isort>=5.12.0; extra == 'dev'
Requires-Dist: mypy>=1.0.0; extra == 'dev'
Requires-Dist: pytest>=7.0.0; extra == 'dev'
Requires-Dist: ruff>=0.1.0; extra == 'dev'
